truesight/__init__.py
truesight/base.py
truesight/core.py
truesight/layers.py
truesight/metrics.py
truesight/models.py
truesight/preprocessing.py
truesight/utils.py
truesight-0.0.3a1.dist-info/LICENSE
truesight-0.0.3a1.dist-info/METADATA
truesight-0.0.3a1.dist-info/WHEEL
truesight-0.0.3a1.dist-info/top_level.txt
truesight-0.0.3a1.dist-info/RECORD
