Metadata-Version: 2.1
Name: truesight
Version: 0.0.3a1
Summary: Truesight is a python package for time series prediction using deep learning and statistical models.
Home-page: https://github.com/renanklehm/true-sight
Download-URL: https://github.com/renanklehm/true-sight/archive/refs/tags/v0.0.1-alpha.tar.gz
Author: Renan Otvin Klehm
Author-email: renanotivin@hotmail.com
Keywords: time series,prediction
License-File: LICENSE
Requires-Dist: tensorflow (>=2.11.0)
Requires-Dist: optuna (>=2.10.1)
Requires-Dist: numpy (>=1.23.5)
Requires-Dist: pandas
Requires-Dist: matplotlib
Requires-Dist: scipy
Requires-Dist: tqdm
